aoc_input_fetcher/__init__.py
aoc_input_fetcher/input_fetcher.py
aoc_input_fetcher-0.1.2.dist-info/LICENSE
aoc_input_fetcher-0.1.2.dist-info/METADATA
aoc_input_fetcher-0.1.2.dist-info/WHEEL
aoc_input_fetcher-0.1.2.dist-info/top_level.txt
aoc_input_fetcher-0.1.2.dist-info/RECORD
