Metadata-Version: 2.1
Name: aoc_input_fetcher
Version: 0.1.2
Summary: A useful tool for getting the input automatically for Advent of Code, given you follow the file structure
Home-page: https://github.com/mourud/aoc-input-fetcher
Author: Mourud Ishmam Ahmed
Author-email: ishmam1@gmail.com
Project-URL: Bug Tracker, https://github.com/mourud/aoc-input-fetcher/issues
Project-URL: Documentation, https://github.com/mourud/aoc-input-fetcher#readme
Keywords: Advent of Code,input fetcher,automation
Classifier: Programming Language :: Python :: 3
Classifier: License :: OSI Approved :: MIT License
Classifier: Operating System :: OS Independent
Requires-Python: >=3.6
License-File: LICENSE
Requires-Dist: requests
Requires-Dist: python-dotenv
